README.md
setup.py
BmobFilterService.egg-info/PKG-INFO
BmobFilterService.egg-info/SOURCES.txt
BmobFilterService.egg-info/dependency_links.txt
BmobFilterService.egg-info/top_level.txt
Service/__init__.py
Service/impl.py
Service/service_interface.py